clickup_mcp/main.py
clickup_mcp/utilities.py
clickup_mcp-0.1.4.dist-info/METADATA
clickup_mcp-0.1.4.dist-info/WHEEL
clickup_mcp-0.1.4.dist-info/entry_points.txt
clickup_mcp-0.1.4.dist-info/top_level.txt
clickup_mcp-0.1.4.dist-info/RECORD
